bitmex_trio_websocket/__init__.py
bitmex_trio_websocket/auth.py
bitmex_trio_websocket/exceptions.py
bitmex_trio_websocket/parser.py
bitmex_trio_websocket/storage.py
bitmex_trio_websocket/websocket.py
bitmex_trio_websocket-0.16.1.dist-info/LICENSE
bitmex_trio_websocket-0.16.1.dist-info/WHEEL
bitmex_trio_websocket-0.16.1.dist-info/METADATA
bitmex_trio_websocket-0.16.1.dist-info/RECORD
