Metadata-Version: 2.1
Name: bitmex-trio-websocket
Version: 0.16.1
Summary: Websocket implementation for BitMEX cryptocurrency derivatives exchange.
Home-page: https://github.com/andersea/bitmex-trio-websocket
License: MIT
Keywords: BitMEX,Trio,Websocket,async
Author: Anders Ellenshøj Andersen
Author-email: andersa@ellenshoej.dk
Requires-Python: >=3.7,<4.0
Classifier: Development Status :: 4 - Beta
Classifier: Framework :: Trio
Classifier: Intended Audience :: Developers
Classifier: License :: OSI Approved :: MIT License
Classifier: Natural Language :: English
Classifier: Programming Language :: Python :: 3
Classifier: Programming Language :: Python :: 3.10
Classifier: Programming Language :: Python :: 3.7
Classifier: Programming Language :: Python :: 3.8
Classifier: Programming Language :: Python :: 3.9
Requires-Dist: async_generator (>=1.10,<2.0)
Requires-Dist: pendulum (>=2.1.2,<3.0.0)
Requires-Dist: slurry-websocket (>=0.4.2,<0.5.0)
Requires-Dist: sortedcontainers (>=2.4.0,<3.0.0)
